tensorPak/1.txt
tensorPak/11.txt
tensorPak/12.txt
tensorPak/13.txt
tensorPak/14.txt
tensorPak/15.txt
tensorPak/16.txt
tensorPak/17.txt
tensorPak/18.txt
tensorPak/19.txt
tensorPak/2.txt
tensorPak/20.txt
tensorPak/3.txt
tensorPak/4.txt
tensorPak/5.txt
tensorPak/__init__.py
tensorPak-1.0.dist-info/METADATA
tensorPak-1.0.dist-info/WHEEL
tensorPak-1.0.dist-info/top_level.txt
tensorPak-1.0.dist-info/RECORD
